LICENSE
MANIFEST.in
README.md
setup.py
threedboard/__init__.py
threedboard/__main__.py
threedboard/data_reader.py
threedboard.egg-info/PKG-INFO
threedboard.egg-info/SOURCES.txt
threedboard.egg-info/dependency_links.txt
threedboard.egg-info/not-zip-safe
threedboard.egg-info/requires.txt
threedboard.egg-info/top_level.txt
threedboard/dashboard_html/404.html
threedboard/dashboard_html/favicon.ico
threedboard/dashboard_html/index.html
threedboard/dashboard_html/vercel.svg
threedboard/dashboard_html/_next/static/chunks/249-cbf785bb47342695e736.js
threedboard/dashboard_html/_next/static/chunks/29107295-2648cb5e919f7c78c7cc.js
threedboard/dashboard_html/_next/static/chunks/e82996df-3710848f24a407443b07.js
threedboard/dashboard_html/_next/static/chunks/framework-c5113a73163ba9a6512c.js
threedboard/dashboard_html/_next/static/chunks/main-71948af4b0f09c0fc30e.js
threedboard/dashboard_html/_next/static/chunks/polyfills-eef578260fd80f8fff94.js
threedboard/dashboard_html/_next/static/chunks/webpack-277c75ec70a3d22a400d.js
threedboard/dashboard_html/_next/static/chunks/pages/_app-fdb16d033bc7d3e356ac.js
threedboard/dashboard_html/_next/static/chunks/pages/_error-b30902e13465df7c5366.js
threedboard/dashboard_html/_next/static/chunks/pages/index-fcfd95bca9361feb82b3.js
threedboard/dashboard_html/_next/static/css/3fc4006626de201e9cab.css
threedboard/dashboard_html/_next/static/x5ecpz1hEBb2ss3lm-Ud6/_buildManifest.js
threedboard/dashboard_html/_next/static/x5ecpz1hEBb2ss3lm-Ud6/_ssgManifest.js