Metadata-Version: 2.1
Name: threedboard
Version: 0.0.8
Summary: Web Interface to visualize the results of 3DB experiments
Home-page: https://github.com/3db/dashboard
Author: 3DB authors
Author-email: leclerc@mit.edu
License: MIT
Platform: UNKNOWN
